scaife_viewer/__init__.py
scaife_viewer/atlas/__init__.py
scaife_viewer/atlas/admin.py
scaife_viewer/atlas/apps.py
scaife_viewer/atlas/chunking_poc.py
scaife_viewer/atlas/compat.py
scaife_viewer/atlas/conf.py
scaife_viewer/atlas/constants.py
scaife_viewer/atlas/data_model.py
scaife_viewer/atlas/db_routers.py
scaife_viewer/atlas/hooks.py
scaife_viewer/atlas/ingestion_pipeline.py
scaife_viewer/atlas/language_utils.py
scaife_viewer/atlas/managers.py
scaife_viewer/atlas/models.py
scaife_viewer/atlas/parallel_tokenizers.py
scaife_viewer/atlas/passage.py
scaife_viewer/atlas/schema.py
scaife_viewer/atlas/tokenizers.py
scaife_viewer/atlas/urls.py
scaife_viewer/atlas/urn.py
scaife_viewer/atlas/utils.py
scaife_viewer/atlas/backports/__init__.py
scaife_viewer/atlas/backports/scaife_viewer/__init__.py
scaife_viewer/atlas/backports/scaife_viewer/cts/__init__.py
scaife_viewer/atlas/backports/scaife_viewer/cts/heal.py
scaife_viewer/atlas/backports/scaife_viewer/cts/passage.py
scaife_viewer/atlas/backports/scaife_viewer/cts/utils.py
scaife_viewer/atlas/backports/scaife_viewer/search/__init__.py
scaife_viewer/atlas/backports/scaife_viewer/search/templates.py
scaife_viewer/atlas/backports/scaife_viewer/search/fixtures/base_template.json
scaife_viewer/atlas/importers/__init__.py
scaife_viewer/atlas/importers/alignments.py
scaife_viewer/atlas/importers/attributions.py
scaife_viewer/atlas/importers/audio_annotations.py
scaife_viewer/atlas/importers/dictionaries.py
scaife_viewer/atlas/importers/image_annotations.py
scaife_viewer/atlas/importers/metadata_collections.py
scaife_viewer/atlas/importers/metrical_annotations.py
scaife_viewer/atlas/importers/named_entities.py
scaife_viewer/atlas/importers/repo_metadata.py
scaife_viewer/atlas/importers/text_annotations.py
scaife_viewer/atlas/importers/tocs.py
scaife_viewer/atlas/importers/token_annotations.py
scaife_viewer/atlas/importers/versions.py
scaife_viewer/atlas/management/__init__.py
scaife_viewer/atlas/management/commands/__init__.py
scaife_viewer_atlas-0.3rc1.dist-info/LICENSE
scaife_viewer_atlas-0.3rc1.dist-info/METADATA
scaife_viewer_atlas-0.3rc1.dist-info/WHEEL
scaife_viewer_atlas-0.3rc1.dist-info/top_level.txt
scaife_viewer_atlas-0.3rc1.dist-info/RECORD
