Metadata-Version: 2.1
Name: scaife-viewer-atlas
Version: 0.3rc1
Summary: Aligned Text and Linguistic Annotation Server (ATLAS)
Home-page: http://github.com/scaife-viewer/backend/
Author: Scaife Viewer Team
Author-email: jtauber+scaife@jtauber.com
License: MIT
Classifier: Development Status :: 3 - Alpha
Classifier: Environment :: Web Environment
Classifier: Framework :: Django
Classifier: Intended Audience :: Developers
Classifier: License :: OSI Approved :: MIT License
Classifier: Operating System :: OS Independent
Classifier: Programming Language :: Python
Classifier: Programming Language :: Python :: 3
Classifier: Topic :: Software Development :: Libraries :: Python Modules
License-File: LICENSE
Requires-Dist: django-appconf >=1.0.4
Requires-Dist: django-extensions <3,>=2.2.6
Requires-Dist: django-filter <3,>=2.3.0
Requires-Dist: django-sortedm2m <3,>=2.0.0
Requires-Dist: django-treebeard <5,>=4.3.0
Requires-Dist: Django <3,>=2.2.15
Requires-Dist: django-jsonfield-backport <2,>=1.0.0
Requires-Dist: graphene-django ==2.6.0
Requires-Dist: PyYAML ==5.4.1
Requires-Dist: importlib-resources <6,>=5.1.2
Requires-Dist: jsonlines <3,>=2.0.0
Requires-Dist: regex >=2020.11.13
Requires-Dist: tqdm <5,>=4.48.2
Provides-Extra: dev
Requires-Dist: black ==19.10b0 ; extra == 'dev'
Requires-Dist: flake8 <4,>=3.7 ; extra == 'dev'
Requires-Dist: flake8-quotes <3,>=2.1.1 ; extra == 'dev'
Requires-Dist: isort <6,>=5.6.4 ; extra == 'dev'
Requires-Dist: pytest-cov <3,>=2.8 ; extra == 'dev'
Requires-Dist: pytest-django <4,>3.7.0 ; extra == 'dev'
Requires-Dist: hypothesis <6,>=5.1.5 ; extra == 'dev'
Provides-Extra: test
Requires-Dist: pytest-cov <3,>=2.8 ; extra == 'test'
Requires-Dist: pytest-django <4,>3.7.0 ; extra == 'test'
Requires-Dist: hypothesis <6,>=5.1.5 ; extra == 'test'
